llama_index/py.typed
llama_index/vector_stores/bigquery/__init__.py
llama_index/vector_stores/bigquery/base.py
llama_index/vector_stores/bigquery/utils.py
llama_index_vector_stores_bigquery-0.1.1.dist-info/METADATA
llama_index_vector_stores_bigquery-0.1.1.dist-info/WHEEL
llama_index_vector_stores_bigquery-0.1.1.dist-info/licenses/LICENSE
llama_index_vector_stores_bigquery-0.1.1.dist-info/RECORD
