Metadata-Version: 2.4
Name: llama-index-vector-stores-bigquery
Version: 0.1.1
Summary: llama-index vector_stores bigquery vector search integration
License-Expression: MIT
License-File: LICENSE
Requires-Python: <4.0,>=3.9
Requires-Dist: google-cloud-bigquery<4,>=3.34.0
Requires-Dist: llama-index-core<0.15,>=0.13.0
